{
    "$schema": "https://raw.githubusercontent.com/Azure/azure-devtestlab/master/schemas/2016-11-28/dtlArtifacts.json",
    "title": "Run BGInfo at logon.",
    "publisher": "JeffGilb",
    "description": "Copies BgInfo v4.21 (by Mark Russinovich) to C:\ProgramData\Bginfo\ and schedules a task to run them at logon.",
    "tags": [
        "Windows"
    ],
    "iconUri": "https://raw.githubusercontent.com/jeffgilb/mydevtestlabs/master/dev/jeffgilb.png",
    "targetOsType": "Windows",
    "runCommand": {
        "commandToExecute": "[concat('powershell.exe -ExecutionPolicy bypass \"& ./bginfo.ps1')]"
    }
}
